mqtt_spb_wrapper/__init__.py
mqtt_spb_wrapper/mqtt_spb_entity.py
mqtt_spb_wrapper/mqtt_spb_entity_app.py
mqtt_spb_wrapper/mqtt_spb_entity_device.py
mqtt_spb_wrapper/mqtt_spb_entity_edgenode.py
mqtt_spb_wrapper/mqtt_spb_entity_scada.py
mqtt_spb_wrapper/spb_base.py
mqtt_spb_wrapper/spb_protobuf/__init__.py
mqtt_spb_wrapper/spb_protobuf/sparkplug_b.py
mqtt_spb_wrapper/spb_protobuf/sparkplug_b_pb2.py
mqtt_spb_wrapper/spb_protobuf/sparkplug_b_tools.py
mqtt_spb_wrapper-2.1.2.dist-info/licenses/LICENSE
mqtt_spb_wrapper-2.1.2.dist-info/METADATA
mqtt_spb_wrapper-2.1.2.dist-info/WHEEL
mqtt_spb_wrapper-2.1.2.dist-info/top_level.txt
mqtt_spb_wrapper-2.1.2.dist-info/RECORD
