Metadata-Version: 2.4
Name: mqtt_spb_wrapper
Version: 2.1.2
Summary: MQTT Sparkplug B v1.0 Wrapper
Author: Javier FG
Project-URL: Homepage, https://github.com/javier-fg/mqtt-spb-wrapper
Keywords: sparkplug,mqtt,ecliplse,tahu,iiot,iot
Classifier: License :: OSI Approved :: Eclipse Public License 2.0 (EPL-2.0)
Classifier: Programming Language :: Python
Classifier: Programming Language :: Python :: 3
Requires-Python: >=3.7
License-File: LICENSE
Requires-Dist: paho_mqtt==1.6.1
Requires-Dist: protobuf==3.20.3
Dynamic: license-file
